icloud_calendar_mcp/__init__.py
icloud_calendar_mcp/__main__.py
icloud_calendar_mcp/cli.py
icloud_calendar_mcp/downloader.py
icloud_calendar_mcp-2.0.0.dist-info/METADATA
icloud_calendar_mcp-2.0.0.dist-info/WHEEL
icloud_calendar_mcp-2.0.0.dist-info/entry_points.txt
icloud_calendar_mcp-2.0.0.dist-info/RECORD
