Metadata-Version: 2.4
Name: icloud-calendar-mcp
Version: 2.0.0
Summary: MCP server for iCloud Calendar access via CalDAV
Project-URL: Homepage, https://github.com/icloud-calendar-mcp/icloud-calendar-mcp
Project-URL: Repository, https://github.com/icloud-calendar-mcp/icloud-calendar-mcp
Project-URL: Issues, https://github.com/icloud-calendar-mcp/icloud-calendar-mcp/issues
Author: Onekash Labs
License-Expression: Apache-2.0
Keywords: ai,caldav,calendar,claude,icloud,mcp,model-context-protocol
Classifier: Development Status :: 4 - Beta
Classifier: Intended Audience :: Developers
Classifier: License :: OSI Approved :: Apache Software License
Classifier: Programming Language :: Python :: 3
Classifier: Programming Language :: Python :: 3.10
Classifier: Programming Language :: Python :: 3.11
Classifier: Programming Language :: Python :: 3.12
Classifier: Topic :: Software Development :: Libraries
Requires-Python: >=3.10
Requires-Dist: httpx>=0.27.0
